synced_collections/__init__.py
synced_collections/_caching.py
synced_collections/errors.py
synced_collections/numpy_utils.py
synced_collections/utils.py
synced_collections/validators.py
synced_collections/version.py
synced_collections/backends/__init__.py
synced_collections/backends/collection_json.py
synced_collections/backends/collection_mongodb.py
synced_collections/backends/collection_redis.py
synced_collections/backends/collection_zarr.py
synced_collections/buffers/__init__.py
synced_collections/buffers/buffered_collection.py
synced_collections/buffers/file_buffered_collection.py
synced_collections/buffers/memory_buffered_collection.py
synced_collections/buffers/serialized_file_buffered_collection.py
synced_collections/data_types/__init__.py
synced_collections/data_types/attr_dict.py
synced_collections/data_types/synced_collection.py
synced_collections/data_types/synced_dict.py
synced_collections/data_types/synced_list.py
synced_collections-1.0.0.dist-info/LICENSE.txt
synced_collections-1.0.0.dist-info/METADATA
synced_collections-1.0.0.dist-info/WHEEL
synced_collections-1.0.0.dist-info/top_level.txt
synced_collections-1.0.0.dist-info/RECORD
