Metadata-Version: 2.1
Name: synced-collections
Version: 1.0.0
Summary: Interact with persistent key-value stores using Pythonic abstractions.
Author-email: "Vyas Ramasubramani et al." <vyas.ramasubramani@gmail.com>
Maintainer-email: signac Developers <signac-support@umich.edu>
License: BSD 3-Clause License for the software synced_collections.
Project-URL: Homepage, https://signac.io
Keywords: database,containers
Classifier: Development Status :: 5 - Production/Stable
Classifier: Intended Audience :: Science/Research
Classifier: License :: OSI Approved :: BSD License
Classifier: Topic :: Database
Classifier: Programming Language :: Python :: 3.8
Classifier: Programming Language :: Python :: 3.9
Classifier: Programming Language :: Python :: 3.10
Classifier: Programming Language :: Python :: 3.11
Classifier: Programming Language :: Python :: Implementation :: CPython
Classifier: Programming Language :: Python :: Implementation :: PyPy
Requires-Python: >=3.8
License-File: LICENSE.txt
Provides-Extra: mongodb
Requires-Dist: pymongo ; extra == 'mongodb'
Provides-Extra: redis
Requires-Dist: redis ; extra == 'redis'
Provides-Extra: zarr
Requires-Dist: zarr ; extra == 'zarr'
